arkprts/__init__.py
arkprts/__main__.py
arkprts/auth.py
arkprts/automation.py
arkprts/client.py
arkprts/errors.py
arkprts/network.py
arkprts/py.typed
arkprts/assets/__init__.py
arkprts/assets/__main__.py
arkprts/assets/base.py
arkprts/assets/bundle.py
arkprts/assets/git.py
arkprts/models/__init__.py
arkprts/models/base.py
arkprts/models/battle.py
arkprts/models/data.py
arkprts/models/social.py
arkprts-0.3.19.dist-info/licenses/LICENSE
arkprts-0.3.19.dist-info/METADATA
arkprts-0.3.19.dist-info/WHEEL
arkprts-0.3.19.dist-info/top_level.txt
arkprts-0.3.19.dist-info/RECORD
