Metadata-Version: 2.4
Name: arkprts
Version: 0.3.19
Summary: Arknights python wrapper.
Home-page: https://github.com/thesadru/arkprts
License: MIT
Requires-Python: >=3.9
License-File: LICENSE
Requires-Dist: aiohttp
Requires-Dist: pydantic==2.*
Provides-Extra: all
Requires-Dist: UnityPy>=1.22.2; extra == "all"
Requires-Dist: rsa; extra == "all"
Requires-Dist: pycryptodome; extra == "all"
Requires-Dist: bson; extra == "all"
Provides-Extra: rsa
Requires-Dist: rsa; extra == "rsa"
Provides-Extra: aes
Requires-Dist: pycryptodome; extra == "aes"
Provides-Extra: assets
Requires-Dist: UnityPy>=1.22.2; extra == "assets"
Requires-Dist: pycryptodome; extra == "assets"
Requires-Dist: bson; extra == "assets"
Dynamic: description
Dynamic: description-content-type
Dynamic: home-page
Dynamic: license
Dynamic: license-file
Dynamic: provides-extra
Dynamic: requires-dist
Dynamic: summary
